[{"code":"031401","name":"Angat"},{"code":"031402","name":"Balagtas (Bigaa)"},{"code":"031403","name":"Baliuag"},{"code":"031404","name":"Bocaue"},{"code":"031405","name":"Bulacan"},{"code":"031406","name":"Bustos"},{"code":"031407","name":"Calumpit"},{"code":"031410","name":"City Of Malolos (Capital)"},{"code":"031412","name":"City Of Meycauayan"},{"code":"031420","name":"City Of San Jose Del Monte"},{"code":"031424","name":"Doña Remedios Trinidad"},{"code":"031408","name":"Guiguinto"},{"code":"031409","name":"Hagonoy"},{"code":"031411","name":"Marilao"},{"code":"031413","name":"Norzagaray"},{"code":"031414","name":"Obando"},{"code":"031415","name":"Pandi"},{"code":"031416","name":"Paombong"},{"code":"031417","name":"Plaridel"},{"code":"031418","name":"Pulilan"},{"code":"031419","name":"San Ildefonso"},{"code":"031421","name":"San Miguel"},{"code":"031422","name":"San Rafael"},{"code":"031423","name":"Santa Maria"}]